anthem/__init__.py
anthem/cli.py
anthem/exceptions.py
anthem/output.py
anthem/lyrics/__init__.py
anthem/lyrics/loaders.py
anthem/lyrics/modules.py
anthem/lyrics/records.py
anthem/lyrics/settings.py
anthem/lyrics/uninstaller.py
anthem/sample_songs/__init__.py
anthem-0.14.0.dist-info/LICENSE
anthem-0.14.0.dist-info/METADATA
anthem-0.14.0.dist-info/WHEEL
anthem-0.14.0.dist-info/entry_points.txt
anthem-0.14.0.dist-info/top_level.txt
anthem-0.14.0.dist-info/RECORD
