Metadata-Version: 2.1
Name: anthem
Version: 0.14.0
Summary: Make your Odoo scripts sing.
Home-page: https://github.com/camptocamp/anthem
Author: Camptocamp
Author-email: info@camptocamp.com
License: LGPLv3+
Classifier: Development Status :: 3 - Alpha
Classifier: Intended Audience :: Developers
Classifier: Natural Language :: English
Classifier: License :: OSI Approved :: GNU Lesser General Public License v3 or later (LGPLv3+)
Classifier: Programming Language :: Python
Classifier: Programming Language :: Python :: 3
Classifier: Programming Language :: Python :: 3 :: Only
Classifier: Programming Language :: Python :: Implementation :: CPython
License-File: LICENSE
Requires-Dist: future
Requires-Dist: unicodecsv
